justaval/__init__.py
justavalue-0.1.dist-info/METADATA
justavalue-0.1.dist-info/WHEEL
justavalue-0.1.dist-info/top_level.txt
justavalue-0.1.dist-info/RECORD
