Metadata-Version: 2.1
Name: justavalue
Version: 0.1
Requires-Dist: aiofiles
